[
  {
    "id": 1,
    "name": "Knives Out",
    "exePath": "F:\\hyxd\\Engine\\Binaries\\Win64\\hyxd.exe",
    "args": "",
    "category": "",
    "group": "",
    "tags": [],
    "platform": "Local",
    "status": "Installed",
    "coverRelPath": "covers/1.png",
    "allowedClientIps": [
      "192.168.1.10",
      "192.168.1.11",
      "192.168.0.163"
    ]
  },
  {
    "id": 2,
    "name": "Valorant",
    "exePath": "C:\\Riot Games\\Riot Client\\RiotClientServices.exe",
    "args": "--launch-product=valorant --launch-patchline=live",
    "category": "Online Games",
    "group": "",
    "tags": [],
    "platform": "Local",
    "status": "Installed",
    "coverRelPath": "covers/2.png",
    "exeIconRelPath": "icons/013a90d1812c0dbf9d697672e6147e1e.png",
    "allowedClientIps": [
      "192.168.0.163"
    ]
  }
]